primed_data_processing/__init__.py
primed_data_processing/arbin_cycler.py
primed_data_processing/cellbuilder.py
primed_data_processing/gamry_eis.py
primed_data_processing/primed_utils.py
primed_data_processing-0.1.0.dist-info/LICENSE
primed_data_processing-0.1.0.dist-info/METADATA
primed_data_processing-0.1.0.dist-info/WHEEL
primed_data_processing-0.1.0.dist-info/top_level.txt
primed_data_processing-0.1.0.dist-info/RECORD
