Metadata-Version: 2.1
Name: primed-data-processing
Version: 0.1.0
Summary: A package for processing data produced at UVic's PRIMED Lab
Author-email: Sean Buchanan <seanbuchanan55@hotmail.com>
Project-URL: Homepage, https://github.com/seanbuchanan-eng/primed_data_processing
Classifier: Programming Language :: Python :: 3
Classifier: License :: OSI Approved :: MIT License
Classifier: Operating System :: Microsoft :: Windows :: Windows 11
Requires-Python: >=3.10
License-File: LICENSE
Requires-Dist: numpy >=1.24.1
Requires-Dist: pandas >=1.5.3
Requires-Dist: openpyxl >=3.1.1
Requires-Dist: matplotlib >=3.6.3
Provides-Extra: test
Requires-Dist: pytest ==7.2.2 ; extra == 'test'
